[
    {
        "tconst": "tt0034613",
        "titleType": "movie",
        "primaryTitle": "The Corpse Vanishes",
        "originalTitle": "The Corpse Vanishes",
        "isAdult": "0",
        "startYear": "1942",
        "endYear": "\\N",
        "runtimeMinutes": "64",
        "genres": "Horror,Sci-Fi"
    },
    {
        "tconst": "tt0035009",
        "titleType": "movie",
        "primaryTitle": "The Mad Monster",
        "originalTitle": "The Mad Monster",
        "isAdult": "0",
        "startYear": "1942",
        "endYear": "\\N",
        "runtimeMinutes": "77",
        "genres": "Drama,Horror,Romance"
    },
    {
        "tconst": "tt0037798",
        "titleType": "movie",
        "primaryTitle": "I Accuse My Parents",
        "originalTitle": "I Accuse My Parents",
        "isAdult": "0",
        "startYear": "1944",
        "endYear": "\\N",
        "runtimeMinutes": "68",
        "genres": "Crime,Drama"
    },
    {
        "tconst": "tt0038387",
        "titleType": "movie",
        "primaryTitle": "The Brute Man",
        "originalTitle": "The Brute Man",
        "isAdult": "0",
        "startYear": "1946",
        "endYear": "\\N",
        "runtimeMinutes": "58",
        "genres": "Drama,Horror,Thriller"
    },
    {
        "tconst": "tt0040500",
        "titleType": "movie",
        "primaryTitle": "Jungle Goddess",
        "originalTitle": "Jungle Goddess",
        "isAdult": "0",
        "startYear": "1948",
        "endYear": "\\N",
        "runtimeMinutes": "62",
        "genres": "Action,Adventure,Crime"
    },
    {
        "tconst": "tt0040530",
        "titleType": "movie",
        "primaryTitle": "Last of the Wild Horses",
        "originalTitle": "Last of the Wild Horses",
        "isAdult": "0",
        "startYear": "1948",
        "endYear": "\\N",
        "runtimeMinutes": "84",
        "genres": "Western"
    },
    {
        "tconst": "tt0042874",
        "titleType": "movie",
        "primaryTitle": "Radar Secret Service",
        "originalTitle": "Radar Secret Service",
        "isAdult": "0",
        "startYear": "1950",
        "endYear": "\\N",
        "runtimeMinutes": "59",
        "genres": "Action,Crime,Drama"
    },
    {
        "tconst": "tt0042897",
        "titleType": "movie",
        "primaryTitle": "Rocketship X-M",
        "originalTitle": "Rocketship X-M",
        "isAdult": "0",
        "startYear": "1950",
        "endYear": "\\N",
        "runtimeMinutes": "77",
        "genres": "Family,Sci-Fi"
    },
    {
        "tconst": "tt0043757",
        "titleType": "movie",
        "primaryTitle": "Lost Continent",
        "originalTitle": "Lost Continent",
        "isAdult": "0",
        "startYear": "1951",
        "endYear": "\\N",
        "runtimeMinutes": "83",
        "genres": "Adventure,Fantasy,Sci-Fi"
    },
    {
        "tconst": "tt0043895",
        "titleType": "movie",
        "primaryTitle": "The Painted Hills",
        "originalTitle": "The Painted Hills",
        "isAdult": "0",
        "startYear": "1951",
        "endYear": "\\N",
        "runtimeMinutes": "68",
        "genres": "Drama,Family,Western"
    },
    {
        "tconst": "tt0043954",
        "titleType": "movie",
        "primaryTitle": "Racket Girls",
        "originalTitle": "Racket Girls",
        "isAdult": "0",
        "startYear": "1951",
        "endYear": "\\N",
        "runtimeMinutes": "70",
        "genres": "Action,Crime,Drama"
    },
    {
        "tconst": "tt0044750",
        "titleType": "movie",
        "primaryTitle": "Invasion, U.S.A.",
        "originalTitle": "Invasion, U.S.A.",
        "isAdult": "0",
        "startYear": "1952",
        "endYear": "\\N",
        "runtimeMinutes": "73",
        "genres": "Drama,Sci-Fi,War"
    },
    {
        "tconst": "tt0045655",
        "titleType": "tvMovie",
        "primaryTitle": "Crash of Moons",
        "originalTitle": "Crash of Moons",
        "isAdult": "0",
        "startYear": "1954",
        "endYear": "\\N",
        "runtimeMinutes": "78",
        "genres": "Adventure,Family,Sci-Fi"
    },
    {
        "tconst": "tt0046213",
        "titleType": "movie",
        "primaryTitle": "Project Moon Base",
        "originalTitle": "Project Moon Base",
        "isAdult": "0",
        "startYear": "1953",
        "endYear": "\\N",
        "runtimeMinutes": "63",
        "genres": "Sci-Fi"
    },
    {
        "tconst": "tt0046248",
        "titleType": "movie",
        "primaryTitle": "Robot Monster",
        "originalTitle": "Robot Monster",
        "isAdult": "0",
        "startYear": "1953",
        "endYear": "\\N",
        "runtimeMinutes": "66",
        "genres": "Comedy,Family,Horror"
    },
    {
        "tconst": "tt0046264",
        "titleType": "movie",
        "primaryTitle": "Sadko",
        "originalTitle": "Sadko",
        "isAdult": "0",
        "startYear": "1953",
        "endYear": "\\N",
        "runtimeMinutes": "85",
        "genres": "Adventure,Fantasy"
    },
    {
        "tconst": "tt0046977",
        "titleType": "movie",
        "primaryTitle": "Fire Maidens of Outer Space",
        "originalTitle": "Fire Maidens from Outer Space",
        "isAdult": "0",
        "startYear": "1956",
        "endYear": "\\N",
        "runtimeMinutes": "80",
        "genres": "Sci-Fi"
    },
    {
        "tconst": "tt0047211",
        "titleType": "tvMovie",
        "primaryTitle": "Manhunt in Space",
        "originalTitle": "Manhunt in Space",
        "isAdult": "0",
        "startYear": "1956",
        "endYear": "\\N",
        "runtimeMinutes": "78",
        "genres": "Adventure,Family,Sci-Fi"
    },
    {
        "tconst": "tt0047577",
        "titleType": "movie",
        "primaryTitle": "This Island Earth",
        "originalTitle": "This Island Earth",
        "isAdult": "0",
        "startYear": "1955",
        "endYear": "\\N",
        "runtimeMinutes": "86",
        "genres": "Horror,Mystery,Sci-Fi"
    },
    {
        "tconst": "tt0047898",
        "titleType": "movie",
        "primaryTitle": "Bride of the Monster",
        "originalTitle": "Bride of the Monster",
        "isAdult": "0",
        "startYear": "1955",
        "endYear": "\\N",
        "runtimeMinutes": "69",
        "genres": "Horror,Sci-Fi"
    },
    {
        "tconst": "tt0048256",
        "titleType": "movie",
        "primaryTitle": "King Dinosaur",
        "originalTitle": "King Dinosaur",
        "isAdult": "0",
        "startYear": "1955",
        "endYear": "\\N",
        "runtimeMinutes": "63",
        "genres": "Adventure,Sci-Fi"
    },
    {
        "tconst": "tt0048554",
        "titleType": "movie",
        "primaryTitle": "Revenge of the Creature",
        "originalTitle": "Revenge of the Creature",
        "isAdult": "0",
        "startYear": "1955",
        "endYear": "\\N",
        "runtimeMinutes": "82",
        "genres": "Horror,Sci-Fi"
    },
    {
        "tconst": "tt0048682",
        "titleType": "movie",
        "primaryTitle": "Swamp Women",
        "originalTitle": "Swamp Women",
        "isAdult": "0",
        "startYear": "1956",
        "endYear": "\\N",
        "runtimeMinutes": "84",
        "genres": "Adventure,Crime,Drama"
    },
    {
        "tconst": "tt0048701",
        "titleType": "movie",
        "primaryTitle": "Teen-Age Crime Wave",
        "originalTitle": "Teen-Age Crime Wave",
        "isAdult": "0",
        "startYear": "1955",
        "endYear": "\\N",
        "runtimeMinutes": "77",
        "genres": "Crime,Drama"
    },
    {
        "tconst": "tt0049287",
        "titleType": "movie",
        "primaryTitle": "Gunslinger",
        "originalTitle": "Gunslinger",
        "isAdult": "0",
        "startYear": "1956",
        "endYear": "\\N",
        "runtimeMinutes": "78",
        "genres": "Western"
    },
    {
        "tconst": "tt0049358",
        "titleType": "movie",
        "primaryTitle": "The Sword and the Dragon",
        "originalTitle": "Ilya Muromets",
        "isAdult": "0",
        "startYear": "1956",
        "endYear": "\\N",
        "runtimeMinutes": "87",
        "genres": "Fantasy"
    },
    {
        "tconst": "tt0049363",
        "titleType": "movie",
        "primaryTitle": "Indestructible Man",
        "originalTitle": "Indestructible Man",
        "isAdult": "0",
        "startYear": "1956",
        "endYear": "\\N",
        "runtimeMinutes": "72",
        "genres": "Crime,Horror,Sci-Fi"
    },
    {
        "tconst": "tt0049370",
        "titleType": "movie",
        "primaryTitle": "It Conquered the World",
        "originalTitle": "It Conquered the World",
        "isAdult": "0",
        "startYear": "1956",
        "endYear": "\\N",
        "runtimeMinutes": "71",
        "genres": "Horror,Sci-Fi"
    },
    {
        "tconst": "tt0049516",
        "titleType": "movie",
        "primaryTitle": "The Mole People",
        "originalTitle": "The Mole People",
        "isAdult": "0",
        "startYear": "1956",
        "endYear": "\\N",
        "runtimeMinutes": "77",
        "genres": "Adventure,Fantasy,Horror"
    },
    {
        "tconst": "tt0049922",
        "titleType": "movie",
        "primaryTitle": "The Violent Years",
        "originalTitle": "The Violent Years",
        "isAdult": "0",
        "startYear": "1956",
        "endYear": "\\N",
        "runtimeMinutes": "65",
        "genres": "Crime,Film-Noir,Thriller"
    },
    {
        "tconst": "tt0050118",
        "titleType": "movie",
        "primaryTitle": "The Amazing Colossal Man",
        "originalTitle": "The Amazing Colossal Man",
        "isAdult": "0",
        "startYear": "1957",
        "endYear": "\\N",
        "runtimeMinutes": "80",
        "genres": "Sci-Fi"
    },
    {
        "tconst": "tt0050177",
        "titleType": "movie",
        "primaryTitle": "Beginning of the End",
        "originalTitle": "Beginning of the End",
        "isAdult": "0",
        "startYear": "1957",
        "endYear": "\\N",
        "runtimeMinutes": "76",
        "genres": "Horror,Sci-Fi"
    },
    {
        "tconst": "tt0050197",
        "titleType": "movie",
        "primaryTitle": "The Black Scorpion",
        "originalTitle": "The Black Scorpion",
        "isAdult": "0",
        "startYear": "1957",
        "endYear": "\\N",
        "runtimeMinutes": "88",
        "genres": "Horror,Sci-Fi"
    },
    {
        "tconst": "tt0050294",
        "titleType": "movie",
        "primaryTitle": "The Deadly Mantis",
        "originalTitle": "The Deadly Mantis",
        "isAdult": "0",
        "startYear": "1957",
        "endYear": "\\N",
        "runtimeMinutes": "79",
        "genres": "Family,Horror,Sci-Fi"
    },
    {
        "tconst": "tt0050381",
        "titleType": "movie",
        "primaryTitle": "Hercules",
        "originalTitle": "Le fatiche di Ercole",
        "isAdult": "0",
        "startYear": "1958",
        "endYear": "\\N",
        "runtimeMinutes": "104",
        "genres": "Adventure,Fantasy,History"
    },
    {
        "tconst": "tt0050530",
        "titleType": "movie",
        "primaryTitle": "I Was a Teenage Werewolf",
        "originalTitle": "I Was a Teenage Werewolf",
        "isAdult": "0",
        "startYear": "1957",
        "endYear": "\\N",
        "runtimeMinutes": "76",
        "genres": "Drama,Fantasy,Horror"
    },
    {
        "tconst": "tt0050717",
        "titleType": "movie",
        "primaryTitle": "The Robot vs. The Aztec Mummy",
        "originalTitle": "La momia azteca contra el robot humano",
        "isAdult": "0",
        "startYear": "1958",
        "endYear": "\\N",
        "runtimeMinutes": "65",
        "genres": "Horror,Sci-Fi"
    },
    {
        "tconst": "tt0050957",
        "titleType": "movie",
        "primaryTitle": "The She-Creature",
        "originalTitle": "The She-Creature",
        "isAdult": "0",
        "startYear": "1956",
        "endYear": "\\N",
        "runtimeMinutes": "77",
        "genres": "Fantasy,Horror,Romance"
    },
    {
        "tconst": "tt0051128",
        "titleType": "movie",
        "primaryTitle": "The Undead",
        "originalTitle": "The Undead",
        "isAdult": "0",
        "startYear": "1957",
        "endYear": "\\N",
        "runtimeMinutes": "71",
        "genres": "Fantasy,Horror"
    },
    {
        "tconst": "tt0051134",
        "titleType": "movie",
        "primaryTitle": "The Unearthly",
        "originalTitle": "The Unearthly",
        "isAdult": "0",
        "startYear": "1957",
        "endYear": "\\N",
        "runtimeMinutes": "73",
        "genres": "Horror,Sci-Fi"
    },
    {
        "tconst": "tt0051139",
        "titleType": "movie",
        "primaryTitle": "Untamed Youth",
        "originalTitle": "Untamed Youth",
        "isAdult": "0",
        "startYear": "1957",
        "endYear": "\\N",
        "runtimeMinutes": "80",
        "genres": "Crime,Drama,Music"
    },
    {
        "tconst": "tt0051570",
        "titleType": "movie",
        "primaryTitle": "The Spider",
        "originalTitle": "Earth vs the Spider",
        "isAdult": "0",
        "startYear": "1958",
        "endYear": "\\N",
        "runtimeMinutes": "73",
        "genres": "Family,Horror,Sci-Fi"
    },
    {
        "tconst": "tt0051993",
        "titleType": "movie",
        "primaryTitle": "Night of the Blood Beast",
        "originalTitle": "Night of the Blood Beast",
        "isAdult": "0",
        "startYear": "1958",
        "endYear": "\\N",
        "runtimeMinutes": "62",
        "genres": "Horror,Sci-Fi"
    },
    {
        "tconst": "tt0052156",
        "titleType": "movie",
        "primaryTitle": "The Saga of the Viking Women and Their Voyage to the Waters of the Great Sea Serpent",
        "originalTitle": "The Saga of the Viking Women and Their Voyage to the Waters of the Great Sea Serpent",
        "isAdult": "0",
        "startYear": "1957",
        "endYear": "\\N",
        "runtimeMinutes": "66",
        "genres": "Action,Adventure,Fantasy"
    },
    {
        "tconst": "tt0052169",
        "titleType": "movie",
        "primaryTitle": "The Screaming Skull",
        "originalTitle": "The Screaming Skull",
        "isAdult": "0",
        "startYear": "1958",
        "endYear": "\\N",
        "runtimeMinutes": "68",
        "genres": "Horror,Thriller"
    },
    {
        "tconst": "tt0052227",
        "titleType": "movie",
        "primaryTitle": "The Space Children",
        "originalTitle": "The Space Children",
        "isAdult": "0",
        "startYear": "1958",
        "endYear": "\\N",
        "runtimeMinutes": "69",
        "genres": "Sci-Fi"
    },
    {
        "tconst": "tt0052279",
        "titleType": "movie",
        "primaryTitle": "Teenage Cave Man",
        "originalTitle": "Teenage Cave Man",
        "isAdult": "0",
        "startYear": "1958",
        "endYear": "\\N",
        "runtimeMinutes": "65",
        "genres": "Adventure,Sci-Fi"
    },
    {
        "tconst": "tt0052286",
        "titleType": "movie",
        "primaryTitle": "Terror from the Year 5000",
        "originalTitle": "Terror from the Year 5000",
        "isAdult": "0",
        "startYear": "1958",
        "endYear": "\\N",
        "runtimeMinutes": "66",
        "genres": "Sci-Fi"
    },
    {
        "tconst": "tt0052289",
        "titleType": "movie",
        "primaryTitle": "The Thing That Couldn't Die",
        "originalTitle": "The Thing That Couldn't Die",
        "isAdult": "0",
        "startYear": "1958",
        "endYear": "\\N",
        "runtimeMinutes": "69",
        "genres": "Horror"
    },
    {
        "tconst": "tt0052320",
        "titleType": "movie",
        "primaryTitle": "The Crawling Eye",
        "originalTitle": "The Trollenberg Terror",
        "isAdult": "0",
        "startYear": "1958",
        "endYear": "\\N",
        "runtimeMinutes": "84",
        "genres": "Horror,Sci-Fi"
    },
    {
        "tconst": "tt0052378",
        "titleType": "movie",
        "primaryTitle": "War of the Colossal Beast",
        "originalTitle": "War of the Colossal Beast",
        "isAdult": "0",
        "startYear": "1958",
        "endYear": "\\N",
        "runtimeMinutes": "69",
        "genres": "Horror,Sci-Fi"
    },
    {
        "tconst": "tt0052646",
        "titleType": "movie",
        "primaryTitle": "The Brain That Wouldn't Die",
        "originalTitle": "The Brain That Wouldn't Die",
        "isAdult": "0",
        "startYear": "1962",
        "endYear": "\\N",
        "runtimeMinutes": "82",
        "genres": "Horror,Sci-Fi"
    },
    {
        "tconst": "tt0052719",
        "titleType": "movie",
        "primaryTitle": "Daddy-O",
        "originalTitle": "Daddy-O",
        "isAdult": "0",
        "startYear": "1958",
        "endYear": "\\N",
        "runtimeMinutes": "74",
        "genres": "Crime,Music,Mystery"
    },
    {
        "tconst": "tt0052782",
        "titleType": "movie",
        "primaryTitle": "Hercules Unchained",
        "originalTitle": "Ercole e la regina di Lidia",
        "isAdult": "0",
        "startYear": "1959",
        "endYear": "\\N",
        "runtimeMinutes": "98",
        "genres": "Adventure,Fantasy"
    },
    {
        "tconst": "tt0052846",
        "titleType": "movie",
        "primaryTitle": "The Giant Gila Monster",
        "originalTitle": "The Giant Gila Monster",
        "isAdult": "0",
        "startYear": "1959",
        "endYear": "\\N",
        "runtimeMinutes": "74",
        "genres": "Horror,Sci-Fi,Thriller"
    },
    {
        "tconst": "tt0052849",
        "titleType": "movie",
        "primaryTitle": "The Girl in Lovers Lane",
        "originalTitle": "The Girl in Lovers Lane",
        "isAdult": "0",
        "startYear": "1960",
        "endYear": "\\N",
        "runtimeMinutes": "78",
        "genres": "Crime,Drama,Romance"
    },
    {
        "tconst": "tt0052850",
        "titleType": "movie",
        "primaryTitle": "Girls Town",
        "originalTitle": "Girls Town",
        "isAdult": "0",
        "startYear": "1959",
        "endYear": "\\N",
        "runtimeMinutes": "90",
        "genres": "Drama"
    },
    {
        "tconst": "tt0052891",
        "titleType": "movie",
        "primaryTitle": "High School Big Shot",
        "originalTitle": "High School Big Shot",
        "isAdult": "0",
        "startYear": "1959",
        "endYear": "\\N",
        "runtimeMinutes": "70",
        "genres": "Crime,Drama"
    },
    {
        "tconst": "tt0052969",
        "titleType": "movie",
        "primaryTitle": "The Killer Shrews",
        "originalTitle": "The Killer Shrews",
        "isAdult": "0",
        "startYear": "1959",
        "endYear": "\\N",
        "runtimeMinutes": "69",
        "genres": "Horror,Sci-Fi"
    },
    {
        "tconst": "tt0053213",
        "titleType": "movie",
        "primaryTitle": "The Rebel Set",
        "originalTitle": "The Rebel Set",
        "isAdult": "0",
        "startYear": "1959",
        "endYear": "\\N",
        "runtimeMinutes": "72",
        "genres": "Crime,Drama"
    },
    {
        "tconst": "tt0053240",
        "titleType": "movie",
        "primaryTitle": "The Day the Earth Froze",
        "originalTitle": "Sampo",
        "isAdult": "0",
        "startYear": "1959",
        "endYear": "\\N",
        "runtimeMinutes": "90",
        "genres": "Adventure,Fantasy"
    },
    {
        "tconst": "tt0053241",
        "titleType": "movie",
        "primaryTitle": "Santa Claus",
        "originalTitle": "Santa Claus",
        "isAdult": "0",
        "startYear": "1959",
        "endYear": "\\N",
        "runtimeMinutes": "94",
        "genres": "Comedy,Family,Fantasy"
    },
    {
        "tconst": "tt0053250",
        "titleType": "movie",
        "primaryTitle": "First Spaceship on Venus",
        "originalTitle": "Der schweigende Stern",
        "isAdult": "0",
        "startYear": "1960",
        "endYear": "\\N",
        "runtimeMinutes": "93",
        "genres": "Sci-Fi"
    },
    {
        "tconst": "tt0053337",
        "titleType": "movie",
        "primaryTitle": "Teenagers from Outer Space",
        "originalTitle": "Teenagers from Outer Space",
        "isAdult": "0",
        "startYear": "1959",
        "endYear": "\\N",
        "runtimeMinutes": "86",
        "genres": "Horror,Sci-Fi,Thriller"
    },
    {
        "tconst": "tt0053464",
        "titleType": "movie",
        "primaryTitle": "Prince of Space",
        "originalTitle": "Yûsei ôji",
        "isAdult": "0",
        "startYear": "1959",
        "endYear": "\\N",
        "runtimeMinutes": "121",
        "genres": "Action,Adventure,Sci-Fi"
    },
    {
        "tconst": "tt0053593",
        "titleType": "movie",
        "primaryTitle": "The Amazing Transparent Man",
        "originalTitle": "The Amazing Transparent Man",
        "isAdult": "0",
        "startYear": "1960",
        "endYear": "\\N",
        "runtimeMinutes": "58",
        "genres": "Horror,Sci-Fi"
    },
    {
        "tconst": "tt0053611",
        "titleType": "movie",
        "primaryTitle": "Attack of the Giant Leeches",
        "originalTitle": "Attack of the Giant Leeches",
        "isAdult": "0",
        "startYear": "1959",
        "endYear": "\\N",
        "runtimeMinutes": "62",
        "genres": "Horror,Sci-Fi"
    },
    {
        "tconst": "tt0053640",
        "titleType": "movie",
        "primaryTitle": "The Beatniks",
        "originalTitle": "The Beatniks",
        "isAdult": "0",
        "startYear": "1960",
        "endYear": "\\N",
        "runtimeMinutes": "78",
        "genres": "Crime"
    },
    {
        "tconst": "tt0053888",
        "titleType": "tvMovie",
        "primaryTitle": "Hamlet",
        "originalTitle": "Hamlet, Prinz von Dänemark",
        "isAdult": "0",
        "startYear": "1960",
        "endYear": "\\N",
        "runtimeMinutes": "152",
        "genres": "Drama,Mystery"
    },
    {
        "tconst": "tt0054020",
        "titleType": "movie",
        "primaryTitle": "The Leech Woman",
        "originalTitle": "The Leech Woman",
        "isAdult": "0",
        "startYear": "1960",
        "endYear": "\\N",
        "runtimeMinutes": "77",
        "genres": "Horror,Romance,Sci-Fi"
    },
    {
        "tconst": "tt0054333",
        "titleType": "movie",
        "primaryTitle": "Horrors of Spider Island",
        "originalTitle": "Ein Toter hing im Netz",
        "isAdult": "0",
        "startYear": "1960",
        "endYear": "\\N",
        "runtimeMinutes": "89",
        "genres": "Horror"
    },
    {
        "tconst": "tt0054393",
        "titleType": "movie",
        "primaryTitle": "Tormented",
        "originalTitle": "Tormented",
        "isAdult": "0",
        "startYear": "1960",
        "endYear": "\\N",
        "runtimeMinutes": "75",
        "genres": "Horror,Thriller"
    },
    {
        "tconst": "tt0054415",
        "titleType": "movie",
        "primaryTitle": "12 to the Moon",
        "originalTitle": "12 to the Moon",
        "isAdult": "0",
        "startYear": "1960",
        "endYear": "\\N",
        "runtimeMinutes": "74",
        "genres": "Sci-Fi"
    },
    {
        "tconst": "tt0054673",
        "titleType": "movie",
        "primaryTitle": "The Beast of Yucca Flats",
        "originalTitle": "The Beast of Yucca Flats",
        "isAdult": "0",
        "startYear": "1961",
        "endYear": "\\N",
        "runtimeMinutes": "54",
        "genres": "Horror,Sci-Fi"
    },
    {
        "tconst": "tt0054691",
        "titleType": "movie",
        "primaryTitle": "Bloodlust!",
        "originalTitle": "Bloodlust!",
        "isAdult": "0",
        "startYear": "1961",
        "endYear": "\\N",
        "runtimeMinutes": "68",
        "genres": "Horror,Thriller"
    },
    {
        "tconst": "tt0054851",
        "titleType": "movie",
        "primaryTitle": "Hercules and the Captive Women",
        "originalTitle": "Ercole alla conquista di Atlantide",
        "isAdult": "0",
        "startYear": "1961",
        "endYear": "\\N",
        "runtimeMinutes": "101",
        "genres": "Adventure,Comedy,Fantasy"
    },
    {
        "tconst": "tt0054938",
        "titleType": "movie",
        "primaryTitle": "Gorgo",
        "originalTitle": "Gorgo",
        "isAdult": "0",
        "startYear": "1961",
        "endYear": "\\N",
        "runtimeMinutes": "78",
        "genres": "Horror,Sci-Fi"
    },
    {
        "tconst": "tt0055294",
        "titleType": "movie",
        "primaryTitle": "The Phantom Planet",
        "originalTitle": "The Phantom Planet",
        "isAdult": "0",
        "startYear": "1961",
        "endYear": "\\N",
        "runtimeMinutes": "82",
        "genres": "Action,Adventure,Sci-Fi"
    },
    {
        "tconst": "tt0055380",
        "titleType": "movie",
        "primaryTitle": "Rocket Attack U.S.A.",
        "originalTitle": "Rocket Attack U.S.A.",
        "isAdult": "0",
        "startYear": "1960",
        "endYear": "\\N",
        "runtimeMinutes": "68",
        "genres": "Thriller"
    },
    {
        "tconst": "tt0055408",
        "titleType": "movie",
        "primaryTitle": "Santo vs. the Vampire Women",
        "originalTitle": "Santo vs. las mujeres vampiro",
        "isAdult": "0",
        "startYear": "1962",
        "endYear": "\\N",
        "runtimeMinutes": "89",
        "genres": "Action,Horror"
    },
    {
        "tconst": "tt0055452",
        "titleType": "movie",
        "primaryTitle": "The Sinister Urge",
        "originalTitle": "The Sinister Urge",
        "isAdult": "0",
        "startYear": "1960",
        "endYear": "\\N",
        "runtimeMinutes": "71",
        "genres": "Crime,Drama,Thriller"
    },
    {
        "tconst": "tt0055562",
        "titleType": "movie",
        "primaryTitle": "Invasion of the Neptune Men",
        "originalTitle": "Uchû Kaisokusen",
        "isAdult": "0",
        "startYear": "1961",
        "endYear": "\\N",
        "runtimeMinutes": "75",
        "genres": "Action,Sci-Fi"
    },
    {
        "tconst": "tt0055946",
        "titleType": "movie",
        "primaryTitle": "Eegah",
        "originalTitle": "Eegah",
        "isAdult": "0",
        "startYear": "1962",
        "endYear": "\\N",
        "runtimeMinutes": "92",
        "genres": "Adventure,Comedy,Fantasy"
    },
    {
        "tconst": "tt0056207",
        "titleType": "movie",
        "primaryTitle": "Colossus and the Headhunters",
        "originalTitle": "Maciste contro i cacciatori di teste",
        "isAdult": "0",
        "startYear": "1963",
        "endYear": "\\N",
        "runtimeMinutes": "81",
        "genres": "Action,Adventure,Romance"
    },
    {
        "tconst": "tt0056211",
        "titleType": "movie",
        "primaryTitle": "The Magic Sword",
        "originalTitle": "The Magic Sword",
        "isAdult": "0",
        "startYear": "1962",
        "endYear": "\\N",
        "runtimeMinutes": "80",
        "genres": "Adventure,Drama,Fantasy"
    },
    {
        "tconst": "tt0056415",
        "titleType": "movie",
        "primaryTitle": "Ring of Terror",
        "originalTitle": "Ring of Terror",
        "isAdult": "0",
        "startYear": "1961",
        "endYear": "\\N",
        "runtimeMinutes": "71",
        "genres": "Drama,Horror"
    },
    {
        "tconst": "tt0056499",
        "titleType": "movie",
        "primaryTitle": "The Slime People",
        "originalTitle": "The Slime People",
        "isAdult": "0",
        "startYear": "1963",
        "endYear": "\\N",
        "runtimeMinutes": "76",
        "genres": "Horror,Sci-Fi"
    },
    {
        "tconst": "tt0056961",
        "titleType": "movie",
        "primaryTitle": "The Crawling Hand",
        "originalTitle": "The Crawling Hand",
        "isAdult": "0",
        "startYear": "1963",
        "endYear": "\\N",
        "runtimeMinutes": "89",
        "genres": "Horror,Sci-Fi"
    },
    {
        "tconst": "tt0057181",
        "titleType": "movie",
        "primaryTitle": "The Incredibly Strange Creatures Who Stopped Living and Became Mixed-Up Zombies!!?",
        "originalTitle": "The Incredibly Strange Creatures Who Stopped Living and Became Mixed-Up Zombies!!?",
        "isAdult": "0",
        "startYear": "1964",
        "endYear": "\\N",
        "runtimeMinutes": "82",
        "genres": "Horror"
    },
    {
        "tconst": "tt0057507",
        "titleType": "movie",
        "primaryTitle": "The Skydivers",
        "originalTitle": "The Skydivers",
        "isAdult": "0",
        "startYear": "1963",
        "endYear": "\\N",
        "runtimeMinutes": "75",
        "genres": "Drama,Sport"
    },
    {
        "tconst": "tt0057859",
        "titleType": "movie",
        "primaryTitle": "Monstrosity",
        "originalTitle": "Monstrosity",
        "isAdult": "0",
        "startYear": "1963",
        "endYear": "\\N",
        "runtimeMinutes": "65",
        "genres": "Horror,Mystery,Sci-Fi"
    },
    {
        "tconst": "tt0057970",
        "titleType": "tvMovie",
        "primaryTitle": "The Creeping Terror",
        "originalTitle": "The Creeping Terror",
        "isAdult": "0",
        "startYear": "1964",
        "endYear": "\\N",
        "runtimeMinutes": "77",
        "genres": "Horror,Sci-Fi"
    },
    {
        "tconst": "tt0058007",
        "titleType": "movie",
        "primaryTitle": "Devil Doll",
        "originalTitle": "Devil Doll",
        "isAdult": "0",
        "startYear": "1964",
        "endYear": "\\N",
        "runtimeMinutes": "81",
        "genres": "Horror"
    },
    {
        "tconst": "tt0058208",
        "titleType": "movie",
        "primaryTitle": "The Horror of Party Beach",
        "originalTitle": "The Horror of Party Beach",
        "isAdult": "0",
        "startYear": "1964",
        "endYear": "\\N",
        "runtimeMinutes": "78",
        "genres": "Horror,Musical"
    },
    {
        "tconst": "tt0058267",
        "titleType": "movie",
        "primaryTitle": "Kitten with a Whip",
        "originalTitle": "Kitten with a Whip",
        "isAdult": "0",
        "startYear": "1964",
        "endYear": "\\N",
        "runtimeMinutes": "83",
        "genres": "Action,Crime,Drama"
    },
    {
        "tconst": "tt0058311",
        "titleType": "movie",
        "primaryTitle": "Hercules Against the Moon Men",
        "originalTitle": "Maciste e la regina di Samar",
        "isAdult": "0",
        "startYear": "1964",
        "endYear": "\\N",
        "runtimeMinutes": "90",
        "genres": "Adventure,Fantasy"
    },
    {
        "tconst": "tt0058374",
        "titleType": "movie",
        "primaryTitle": "Frosty",
        "originalTitle": "Morozko",
        "isAdult": "0",
        "startYear": "1965",
        "endYear": "\\N",
        "runtimeMinutes": "84",
        "genres": "Comedy,Family,Fantasy"
    },
    {
        "tconst": "tt0058548",
        "titleType": "movie",
        "primaryTitle": "Santa Claus Conquers the Martians",
        "originalTitle": "Santa Claus Conquers the Martians",
        "isAdult": "0",
        "startYear": "1964",
        "endYear": "\\N",
        "runtimeMinutes": "81",
        "genres": "Adventure,Comedy,Family"
    },
    {
        "tconst": "tt0058615",
        "titleType": "movie",
        "primaryTitle": "The Starfighters",
        "originalTitle": "The Starfighters",
        "isAdult": "0",
        "startYear": "1964",
        "endYear": "\\N",
        "runtimeMinutes": "78",
        "genres": "Drama"
    },
    {
        "tconst": "tt0059080",
        "titleType": "movie",
        "primaryTitle": "Gamera: The Giant Monster",
        "originalTitle": "Daikaijû Gamera",
        "isAdult": "0",
        "startYear": "1965",
        "endYear": "\\N",
        "runtimeMinutes": "78",
        "genres": "Action,Horror,Sci-Fi"
    },
    {
        "tconst": "tt0059161",
        "titleType": "tvMovie",
        "primaryTitle": "Attack of the Eye Creatures",
        "originalTitle": "The Eye Creatures",
        "isAdult": "0",
        "startYear": "1967",
        "endYear": "\\N",
        "runtimeMinutes": "80",
        "genres": "Comedy,Horror,Sci-Fi"
    },
    {
        "tconst": "tt0059290",
        "titleType": "movie",
        "primaryTitle": "The Human Duplicators",
        "originalTitle": "The Human Duplicators",
        "isAdult": "0",
        "startYear": "1965",
        "endYear": "\\N",
        "runtimeMinutes": "100",
        "genres": "Horror,Sci-Fi"
    },
    {
        "tconst": "tt0059464",
        "titleType": "movie",
        "primaryTitle": "Monster a Go-Go",
        "originalTitle": "Monster a Go-Go",
        "isAdult": "0",
        "startYear": "1965",
        "endYear": "\\N",
        "runtimeMinutes": "68",
        "genres": "Horror,Sci-Fi"
    },
    {
        "tconst": "tt0059786",
        "titleType": "movie",
        "primaryTitle": "Teenage Strangler",
        "originalTitle": "Teen-Age Strangler",
        "isAdult": "0",
        "startYear": "1964",
        "endYear": "\\N",
        "runtimeMinutes": "61",
        "genres": "Crime,Drama,Horror"
    },
    {
        "tconst": "tt0059878",
        "titleType": "movie",
        "primaryTitle": "Village of the Giants",
        "originalTitle": "Village of the Giants",
        "isAdult": "0",
        "startYear": "1965",
        "endYear": "\\N",
        "runtimeMinutes": "81",
        "genres": "Comedy,Sci-Fi"
    },
    {
        "tconst": "tt0060074",
        "titleType": "movie",
        "primaryTitle": "Agent for H.A.R.M.",
        "originalTitle": "Agent for H.A.R.M.",
        "isAdult": "0",
        "startYear": "1966",
        "endYear": "\\N",
        "runtimeMinutes": "84",
        "genres": "Action,Adventure,Sci-Fi"
    },
    {
        "tconst": "tt0060446",
        "titleType": "movie",
        "primaryTitle": "Gamera vs. Barugon",
        "originalTitle": "Daikaijû kettô: Gamera tai Barugon",
        "isAdult": "0",
        "startYear": "1966",
        "endYear": "\\N",
        "runtimeMinutes": "106",
        "genres": "Action,Adventure,Fantasy"
    },
    {
        "tconst": "tt0060464",
        "titleType": "movie",
        "primaryTitle": "Ebirah, Horror of the Deep",
        "originalTitle": "Gojira, Ebirâ, Mosura: Nankai no daiketto",
        "isAdult": "0",
        "startYear": "1966",
        "endYear": "\\N",
        "runtimeMinutes": "87",
        "genres": "Action,Adventure,Fantasy"
    },
    {
        "tconst": "tt0060666",
        "titleType": "movie",
        "primaryTitle": "Manos: The Hands of Fate",
        "originalTitle": "Manos: The Hands of Fate",
        "isAdult": "0",
        "startYear": "1966",
        "endYear": "\\N",
        "runtimeMinutes": "70",
        "genres": "Horror"
    },
    {
        "tconst": "tt0060753",
        "titleType": "movie",
        "primaryTitle": "Red Zone Cuba",
        "originalTitle": "Night Train to Mundo Fine",
        "isAdult": "0",
        "startYear": "1966",
        "endYear": "\\N",
        "runtimeMinutes": "89",
        "genres": "Action,Adventure,Crime"
    },
    {
        "tconst": "tt0060956",
        "titleType": "movie",
        "primaryTitle": "Secret Agent Super Dragon",
        "originalTitle": "New York chiama Superdrago",
        "isAdult": "0",
        "startYear": "1966",
        "endYear": "\\N",
        "runtimeMinutes": "100",
        "genres": "Mystery,Thriller"
    },
    {
        "tconst": "tt0061191",
        "titleType": "movie",
        "primaryTitle": "The Wild World of Batwoman",
        "originalTitle": "The Wild World of Batwoman",
        "isAdult": "0",
        "startYear": "1966",
        "endYear": "\\N",
        "runtimeMinutes": "70",
        "genres": "Comedy,Music,Sci-Fi"
    },
    {
        "tconst": "tt0061203",
        "titleType": "movie",
        "primaryTitle": "Women of the Prehistoric Planet",
        "originalTitle": "Women of the Prehistoric Planet",
        "isAdult": "0",
        "startYear": "1966",
        "endYear": "\\N",
        "runtimeMinutes": "90",
        "genres": "Action,Adventure,Romance"
    },
    {
        "tconst": "tt0061456",
        "titleType": "movie",
        "primaryTitle": "Catalina Caper",
        "originalTitle": "Catalina Caper",
        "isAdult": "0",
        "startYear": "1967",
        "endYear": "\\N",
        "runtimeMinutes": "84",
        "genres": "Comedy,Musical,Mystery"
    },
    {
        "tconst": "tt0061557",
        "titleType": "movie",
        "primaryTitle": "The Deadly Bees",
        "originalTitle": "The Deadly Bees",
        "isAdult": "0",
        "startYear": "1966",
        "endYear": "\\N",
        "runtimeMinutes": "84",
        "genres": "Drama,Horror,Mystery"
    },
    {
        "tconst": "tt0061671",
        "titleType": "movie",
        "primaryTitle": "Five the Hard Way",
        "originalTitle": "Five the Hard Way",
        "isAdult": "0",
        "startYear": "1969",
        "endYear": "\\N",
        "runtimeMinutes": "82",
        "genres": "Action,Sport"
    },
    {
        "tconst": "tt0061695",
        "titleType": "movie",
        "primaryTitle": "Gamera vs. Gyaos",
        "originalTitle": "Daikaijû kûchûsen: Gamera tai Gyaosu",
        "isAdult": "0",
        "startYear": "1967",
        "endYear": "\\N",
        "runtimeMinutes": "86",
        "genres": "Action,Family,Fantasy"
    },
    {
        "tconst": "tt0061759",
        "titleType": "movie",
        "primaryTitle": "The Hellcats",
        "originalTitle": "The Hellcats",
        "isAdult": "0",
        "startYear": "1968",
        "endYear": "\\N",
        "runtimeMinutes": "90",
        "genres": "Sport,Thriller"
    },
    {
        "tconst": "tt0061976",
        "titleType": "movie",
        "primaryTitle": "The Million Eyes of Sumuru",
        "originalTitle": "The Million Eyes of Sumuru",
        "isAdult": "0",
        "startYear": "1967",
        "endYear": "\\N",
        "runtimeMinutes": "95",
        "genres": "Action,Adventure"
    },
    {
        "tconst": "tt0062035",
        "titleType": "movie",
        "primaryTitle": "Danger!! Death Ray",
        "originalTitle": "Il raggio infernale",
        "isAdult": "0",
        "startYear": "1967",
        "endYear": "\\N",
        "runtimeMinutes": "93",
        "genres": "Adventure,Sci-Fi"
    },
    {
        "tconst": "tt0062078",
        "titleType": "movie",
        "primaryTitle": "Operation Kid Brother",
        "originalTitle": "OK Connery",
        "isAdult": "0",
        "startYear": "1967",
        "endYear": "\\N",
        "runtimeMinutes": "104",
        "genres": "Action,Comedy,Thriller"
    },
    {
        "tconst": "tt0062159",
        "titleType": "movie",
        "primaryTitle": "The Projected Man",
        "originalTitle": "The Projected Man",
        "isAdult": "0",
        "startYear": "1966",
        "endYear": "\\N",
        "runtimeMinutes": "77",
        "genres": "Horror,Sci-Fi"
    },
    {
        "tconst": "tt0062493",
        "titleType": "movie",
        "primaryTitle": "The Wild Rebels",
        "originalTitle": "The Wild Rebels",
        "isAdult": "0",
        "startYear": "1967",
        "endYear": "\\N",
        "runtimeMinutes": "90",
        "genres": "Crime,Drama,Sport"
    },
    {
        "tconst": "tt0062582",
        "titleType": "tvSeries",
        "primaryTitle": "Mighty Jack",
        "originalTitle": "Maitei Jyakku",
        "isAdult": "0",
        "startYear": "1968",
        "endYear": "\\N",
        "runtimeMinutes": "\\N",
        "genres": "Action,Sci-Fi"
    },
    {
        "tconst": "tt0062861",
        "titleType": "movie",
        "primaryTitle": "Danger: Diabolik",
        "originalTitle": "Diabolik",
        "isAdult": "0",
        "startYear": "1968",
        "endYear": "\\N",
        "runtimeMinutes": "105",
        "genres": "Action,Comedy,Crime"
    },
    {
        "tconst": "tt0063300",
        "titleType": "tvMovie",
        "primaryTitle": "Mighty Jack",
        "originalTitle": "Mighty Jack",
        "isAdult": "0",
        "startYear": "1968",
        "endYear": "\\N",
        "runtimeMinutes": "95",
        "genres": "Action,Sci-Fi"
    },
    {
        "tconst": "tt0064338",
        "titleType": "movie",
        "primaryTitle": "The Castle of Fu Manchu",
        "originalTitle": "The Castle of Fu Manchu",
        "isAdult": "0",
        "startYear": "1969",
        "endYear": "\\N",
        "runtimeMinutes": "92",
        "genres": "Adventure,Crime,Horror"
    },
    {
        "tconst": "tt0064360",
        "titleType": "movie",
        "primaryTitle": "Gamera vs. Guiron",
        "originalTitle": "Gamera tai daiakuju Giron",
        "isAdult": "0",
        "startYear": "1969",
        "endYear": "\\N",
        "runtimeMinutes": "82",
        "genres": "Action,Adventure,Family"
    },
    {
        "tconst": "tt0064639",
        "titleType": "movie",
        "primaryTitle": "Marooned",
        "originalTitle": "Marooned",
        "isAdult": "0",
        "startYear": "1969",
        "endYear": "\\N",
        "runtimeMinutes": "134",
        "genres": "Adventure,Drama,Sci-Fi"
    },
    {
        "tconst": "tt0064691",
        "titleType": "movie",
        "primaryTitle": "Moon Zero Two",
        "originalTitle": "Moon Zero Two",
        "isAdult": "0",
        "startYear": "1969",
        "endYear": "\\N",
        "runtimeMinutes": "100",
        "genres": "Crime,Sci-Fi"
    },
    {
        "tconst": "tt0065343",
        "titleType": "tvSeries",
        "primaryTitle": "San Francisco International Airport",
        "originalTitle": "San Francisco International Airport",
        "isAdult": "0",
        "startYear": "1970",
        "endYear": "1971",
        "runtimeMinutes": "60",
        "genres": "Drama"
    },
    {
        "tconst": "tt0066476",
        "titleType": "movie",
        "primaryTitle": "The Touch of Satan",
        "originalTitle": "The Touch of Satan",
        "isAdult": "0",
        "startYear": "1971",
        "endYear": "\\N",
        "runtimeMinutes": "90",
        "genres": "Horror"
    },
    {
        "tconst": "tt0067123",
        "titleType": "movie",
        "primaryTitle": "Gamera vs. Zigra",
        "originalTitle": "Gamera tai Shinkai kaijû Jigura",
        "isAdult": "0",
        "startYear": "1971",
        "endYear": "\\N",
        "runtimeMinutes": "87",
        "genres": "Action,Adventure,Family"
    },
    {
        "tconst": "tt0070122",
        "titleType": "movie",
        "primaryTitle": "Godzilla vs. Megalon",
        "originalTitle": "Gojira tai Megaro",
        "isAdult": "0",
        "startYear": "1973",
        "endYear": "\\N",
        "runtimeMinutes": "81",
        "genres": "Action,Adventure,Family"
    },
    {
        "tconst": "tt0070531",
        "titleType": "movie",
        "primaryTitle": "Phase IV",
        "originalTitle": "Phase IV",
        "isAdult": "0",
        "startYear": "1974",
        "endYear": "\\N",
        "runtimeMinutes": "84",
        "genres": "Horror,Sci-Fi,Thriller"
    },
    {
        "tconst": "tt0070742",
        "titleType": "tvMovie",
        "primaryTitle": "The Stranger",
        "originalTitle": "The Stranger",
        "isAdult": "0",
        "startYear": "1973",
        "endYear": "\\N",
        "runtimeMinutes": "100",
        "genres": "Sci-Fi"
    },
    {
        "tconst": "tt0071198",
        "titleType": "movie",
        "primaryTitle": "The Bat People",
        "originalTitle": "The Bat People",
        "isAdult": "0",
        "startYear": "1974",
        "endYear": "\\N",
        "runtimeMinutes": "93",
        "genres": "Horror,Romance"
    },
    {
        "tconst": "tt0072666",
        "titleType": "movie",
        "primaryTitle": "Zaat",
        "originalTitle": "Zaat",
        "isAdult": "0",
        "startYear": "1971",
        "endYear": "\\N",
        "runtimeMinutes": "100",
        "genres": "Horror,Sci-Fi"
    },
    {
        "tconst": "tt0073043",
        "titleType": "movie",
        "primaryTitle": "The Giant Spider Invasion",
        "originalTitle": "The Giant Spider Invasion",
        "isAdult": "0",
        "startYear": "1975",
        "endYear": "\\N",
        "runtimeMinutes": "84",
        "genres": "Horror,Sci-Fi"
    },
    {
        "tconst": "tt0073396",
        "titleType": "movie",
        "primaryTitle": "Mitchell",
        "originalTitle": "Mitchell",
        "isAdult": "0",
        "startYear": "1975",
        "endYear": "\\N",
        "runtimeMinutes": "97",
        "genres": "Action,Crime,Drama"
    },
    {
        "tconst": "tt0074350",
        "titleType": "tvMovie",
        "primaryTitle": "Cosmic Princess",
        "originalTitle": "Cosmic Princess",
        "isAdult": "0",
        "startYear": "1982",
        "endYear": "\\N",
        "runtimeMinutes": "91",
        "genres": "Adventure,Drama,Sci-Fi"
    },
    {
        "tconst": "tt0074568",
        "titleType": "tvEpisode",
        "primaryTitle": "Pilot",
        "originalTitle": "Pilot",
        "isAdult": "0",
        "startYear": "1976",
        "endYear": "\\N",
        "runtimeMinutes": "100",
        "genres": "Action,Adventure,Sci-Fi"
    },
    {
        "tconst": "tt0075261",
        "titleType": "movie",
        "primaryTitle": "Squirm",
        "originalTitle": "Squirm",
        "isAdult": "0",
        "startYear": "1976",
        "endYear": "\\N",
        "runtimeMinutes": "92",
        "genres": "Horror"
    },
    {
        "tconst": "tt0075343",
        "titleType": "movie",
        "primaryTitle": "Track of the Moon Beast",
        "originalTitle": "Track of the Moon Beast",
        "isAdult": "0",
        "startYear": "1976",
        "endYear": "\\N",
        "runtimeMinutes": "90",
        "genres": "Horror,Sci-Fi"
    },
    {
        "tconst": "tt0075862",
        "titleType": "tvMovie",
        "primaryTitle": "Code Name: Diamond Head",
        "originalTitle": "Code Name: Diamond Head",
        "isAdult": "0",
        "startYear": "1977",
        "endYear": "\\N",
        "runtimeMinutes": "78",
        "genres": "Action,Crime,Drama"
    },
    {
        "tconst": "tt0076191",
        "titleType": "movie",
        "primaryTitle": "The Incredible Melting Man",
        "originalTitle": "The Incredible Melting Man",
        "isAdult": "0",
        "startYear": "1977",
        "endYear": "\\N",
        "runtimeMinutes": "86",
        "genres": "Horror,Sci-Fi"
    },
    {
        "tconst": "tt0076650",
        "titleType": "tvMovie",
        "primaryTitle": "SST: Death Flight",
        "originalTitle": "SST: Death Flight",
        "isAdult": "0",
        "startYear": "1977",
        "endYear": "\\N",
        "runtimeMinutes": "89",
        "genres": "Adventure,Drama"
    },
    {
        "tconst": "tt0077834",
        "titleType": "movie",
        "primaryTitle": "Laserblast",
        "originalTitle": "Laserblast",
        "isAdult": "0",
        "startYear": "1978",
        "endYear": "\\N",
        "runtimeMinutes": "85",
        "genres": "Horror,Sci-Fi"
    },
    {
        "tconst": "tt0078062",
        "titleType": "movie",
        "primaryTitle": "The Clonus Horror",
        "originalTitle": "The Clonus Horror",
        "isAdult": "0",
        "startYear": "1979",
        "endYear": "\\N",
        "runtimeMinutes": "90",
        "genres": "Horror,Romance,Sci-Fi"
    },
    {
        "tconst": "tt0078345",
        "titleType": "tvMovie",
        "primaryTitle": "Superdome",
        "originalTitle": "Superdome",
        "isAdult": "0",
        "startYear": "1978",
        "endYear": "\\N",
        "runtimeMinutes": "100",
        "genres": "Crime,Drama,Sport"
    },
    {
        "tconst": "tt0078778",
        "titleType": "movie",
        "primaryTitle": "Angels' Brigade",
        "originalTitle": "Angels' Brigade",
        "isAdult": "0",
        "startYear": "1979",
        "endYear": "\\N",
        "runtimeMinutes": "97",
        "genres": "Action,Comedy"
    },
    {
        "tconst": "tt0078976",
        "titleType": "movie",
        "primaryTitle": "City on Fire",
        "originalTitle": "City on Fire",
        "isAdult": "0",
        "startYear": "1979",
        "endYear": "\\N",
        "runtimeMinutes": "106",
        "genres": "Action,Drama"
    },
    {
        "tconst": "tt0080836",
        "titleType": "movie",
        "primaryTitle": "Hangar 18",
        "originalTitle": "Hangar 18",
        "isAdult": "0",
        "startYear": "1980",
        "endYear": "\\N",
        "runtimeMinutes": "97",
        "genres": "Sci-Fi"
    },
    {
        "tconst": "tt0081693",
        "titleType": "movie",
        "primaryTitle": "The Pumaman",
        "originalTitle": "L'uomo puma",
        "isAdult": "0",
        "startYear": "1980",
        "endYear": "\\N",
        "runtimeMinutes": "90",
        "genres": "Action,Adventure,Family"
    },
    {
        "tconst": "tt0082642",
        "titleType": "movie",
        "primaryTitle": "The Last Chase",
        "originalTitle": "The Last Chase",
        "isAdult": "0",
        "startYear": "1981",
        "endYear": "\\N",
        "runtimeMinutes": "101",
        "genres": "Action,Adventure,Sci-Fi"
    },
    {
        "tconst": "tt0084796",
        "titleType": "movie",
        "primaryTitle": "Time Walker",
        "originalTitle": "Time Walker",
        "isAdult": "0",
        "startYear": "1982",
        "endYear": "\\N",
        "runtimeMinutes": "83",
        "genres": "Horror,Sci-Fi"
    },
    {
        "tconst": "tt0085830",
        "titleType": "movie",
        "primaryTitle": "Legend of Dinosaurs and Monster Birds",
        "originalTitle": "Kyôryû kaichô no densetsu",
        "isAdult": "0",
        "startYear": "1977",
        "endYear": "\\N",
        "runtimeMinutes": "92",
        "genres": "Sci-Fi"
    },
    {
        "tconst": "tt0086026",
        "titleType": "movie",
        "primaryTitle": "Extra Terrestrial Visitors",
        "originalTitle": "Los nuevos extraterrestres",
        "isAdult": "0",
        "startYear": "1983",
        "endYear": "\\N",
        "runtimeMinutes": "80",
        "genres": "Drama,Fantasy,Horror"
    },
    {
        "tconst": "tt0086972",
        "titleType": "movie",
        "primaryTitle": "The Blade Master",
        "originalTitle": "Ator 2: L'invincibile Orion",
        "isAdult": "0",
        "startYear": "1982",
        "endYear": "\\N",
        "runtimeMinutes": "92",
        "genres": "Action,Adventure,Fantasy"
    },
    {
        "tconst": "tt0087258",
        "titleType": "movie",
        "primaryTitle": "Final Justice",
        "originalTitle": "Final Justice",
        "isAdult": "0",
        "startYear": "1984",
        "endYear": "\\N",
        "runtimeMinutes": "90",
        "genres": "Action,Crime,Drama"
    },
    {
        "tconst": "tt0088100",
        "titleType": "movie",
        "primaryTitle": "Devil Fish",
        "originalTitle": "Shark: Rosso nell'oceano",
        "isAdult": "0",
        "startYear": "1984",
        "endYear": "\\N",
        "runtimeMinutes": "90",
        "genres": "Action,Adventure,Comedy"
    },
    {
        "tconst": "tt0088380",
        "titleType": "movie",
        "primaryTitle": "Warrior of the Lost World",
        "originalTitle": "Warrior of the Lost World",
        "isAdult": "0",
        "startYear": "1984",
        "endYear": "\\N",
        "runtimeMinutes": "92",
        "genres": "Action,Sci-Fi,Thriller"
    },
    {
        "tconst": "tt0088772",
        "titleType": "movie",
        "primaryTitle": "Boggy Creek II: And the Legend Continues",
        "originalTitle": "The Barbaric Beast of Boggy Creek, Part II",
        "isAdult": "0",
        "startYear": "1983",
        "endYear": "\\N",
        "runtimeMinutes": "91",
        "genres": "Adventure,Drama,Horror"
    },
    {
        "tconst": "tt0088925",
        "titleType": "movie",
        "primaryTitle": "City Limits",
        "originalTitle": "City Limits",
        "isAdult": "0",
        "startYear": "1984",
        "endYear": "\\N",
        "runtimeMinutes": "86",
        "genres": "Action,Adventure,Sci-Fi"
    },
    {
        "tconst": "tt0089104",
        "titleType": "movie",
        "primaryTitle": "Escape from the Bronx",
        "originalTitle": "Fuga dal Bronx",
        "isAdult": "0",
        "startYear": "1983",
        "endYear": "\\N",
        "runtimeMinutes": "89",
        "genres": "Action,Sci-Fi,Thriller"
    },
    {
        "tconst": "tt0089280",
        "titleType": "movie",
        "primaryTitle": "Hobgoblins",
        "originalTitle": "Hobgoblins",
        "isAdult": "0",
        "startYear": "1988",
        "endYear": "\\N",
        "runtimeMinutes": "88",
        "genres": "Comedy,Horror,Sci-Fi"
    },
    {
        "tconst": "tt0089759",
        "titleType": "tvEpisode",
        "primaryTitle": "Overdrawn at the Memory Bank",
        "originalTitle": "Overdrawn at the Memory Bank",
        "isAdult": "0",
        "startYear": "1983",
        "endYear": "\\N",
        "runtimeMinutes": "83",
        "genres": "Comedy,Drama,Romance"
    },
    {
        "tconst": "tt0092297",
        "titleType": "movie",
        "primaryTitle": "Zombie Nightmare",
        "originalTitle": "Zombie Nightmare",
        "isAdult": "0",
        "startYear": "1987",
        "endYear": "\\N",
        "runtimeMinutes": "89",
        "genres": "Fantasy,Horror"
    },
    {
        "tconst": "tt0092532",
        "titleType": "movie",
        "primaryTitle": "Alien from L.A.",
        "originalTitle": "Alien from L.A.",
        "isAdult": "0",
        "startYear": "1988",
        "endYear": "\\N",
        "runtimeMinutes": "87",
        "genres": "Adventure,Comedy,Sci-Fi"
    },
    {
        "tconst": "tt0093872",
        "titleType": "movie",
        "primaryTitle": "Robot Holocaust",
        "originalTitle": "Robot Holocaust",
        "isAdult": "0",
        "startYear": "1987",
        "endYear": "\\N",
        "runtimeMinutes": "79",
        "genres": "Sci-Fi"
    },
    {
        "tconst": "tt0094153",
        "titleType": "tvMovie",
        "primaryTitle": "Time of the Apes",
        "originalTitle": "Time of the Apes",
        "isAdult": "0",
        "startYear": "1987",
        "endYear": "\\N",
        "runtimeMinutes": "97",
        "genres": "Action,Fantasy,Sci-Fi"
    },
    {
        "tconst": "tt0096149",
        "titleType": "movie",
        "primaryTitle": "Space Mutiny",
        "originalTitle": "Space Mutiny",
        "isAdult": "0",
        "startYear": "1988",
        "endYear": "\\N",
        "runtimeMinutes": "91",
        "genres": "Action,Adventure,Romance"
    },
    {
        "tconst": "tt0097174",
        "titleType": "movie",
        "primaryTitle": "Deathstalker and the Warriors from Hell",
        "originalTitle": "Deathstalker and the Warriors from Hell",
        "isAdult": "0",
        "startYear": "1988",
        "endYear": "\\N",
        "runtimeMinutes": "86",
        "genres": "Action,Adventure,Fantasy"
    },
    {
        "tconst": "tt0098048",
        "titleType": "movie",
        "primaryTitle": "Gor II",
        "originalTitle": "Outlaw of Gor",
        "isAdult": "0",
        "startYear": "1988",
        "endYear": "\\N",
        "runtimeMinutes": "89",
        "genres": "Action,Fantasy,Sci-Fi"
    },
    {
        "tconst": "tt0100665",
        "titleType": "movie",
        "primaryTitle": "Soultaker",
        "originalTitle": "Soultaker",
        "isAdult": "0",
        "startYear": "1990",
        "endYear": "\\N",
        "runtimeMinutes": "94",
        "genres": "Fantasy,Horror"
    },
    {
        "tconst": "tt0104463",
        "titleType": "movie",
        "primaryTitle": "Humanoids from Atlantis",
        "originalTitle": "Humanoids from Atlantis",
        "isAdult": "0",
        "startYear": "1992",
        "endYear": "\\N",
        "runtimeMinutes": "45",
        "genres": "Action,Comedy,Sci-Fi"
    },
    {
        "tconst": "tt0106682",
        "titleType": "video",
        "primaryTitle": "The Dead Talk Back",
        "originalTitle": "The Dead Talk Back",
        "isAdult": "0",
        "startYear": "1994",
        "endYear": "\\N",
        "runtimeMinutes": "65",
        "genres": "Crime,Horror,Mystery"
    },
    {
        "tconst": "tt0107910",
        "titleType": "video",
        "primaryTitle": "Quest of the Delta Knights",
        "originalTitle": "Quest of the Delta Knights",
        "isAdult": "0",
        "startYear": "1993",
        "endYear": "\\N",
        "runtimeMinutes": "97",
        "genres": "Action,Adventure,Comedy"
    },
    {
        "tconst": "tt0113135",
        "titleType": "video",
        "primaryTitle": "Future War",
        "originalTitle": "Future War",
        "isAdult": "0",
        "startYear": "1997",
        "endYear": "\\N",
        "runtimeMinutes": "90",
        "genres": "Action,Fantasy,Sci-Fi"
    },
    {
        "tconst": "tt0118137",
        "titleType": "video",
        "primaryTitle": "Werewolf",
        "originalTitle": "Werewolf",
        "isAdult": "0",
        "startYear": "1995",
        "endYear": "\\N",
        "runtimeMinutes": "99",
        "genres": "Horror"
    },
    {
        "tconst": "tt0128224",
        "titleType": "tvMovie",
        "primaryTitle": "Fugitive Alien",
        "originalTitle": "Fugitive Alien",
        "isAdult": "0",
        "startYear": "1986",
        "endYear": "\\N",
        "runtimeMinutes": "102",
        "genres": "Action,Sci-Fi"
    },
    {
        "tconst": "tt0128273",
        "titleType": "movie",
        "primaryTitle": "Invaders from the Deep",
        "originalTitle": "Invaders from the Deep",
        "isAdult": "0",
        "startYear": "1981",
        "endYear": "\\N",
        "runtimeMinutes": "92",
        "genres": "Sci-Fi"
    },
    {
        "tconst": "tt0131028",
        "titleType": "tvMovie",
        "primaryTitle": "Star Force: Fugitive Alien II",
        "originalTitle": "Star Force: Fugitive Alien II",
        "isAdult": "0",
        "startYear": "1987",
        "endYear": "\\N",
        "runtimeMinutes": "75",
        "genres": "Sci-Fi"
    },
    {
        "tconst": "tt0131550",
        "titleType": "video",
        "primaryTitle": "The Final Sacrifice",
        "originalTitle": "The Final Sacrifice",
        "isAdult": "0",
        "startYear": "1990",
        "endYear": "\\N",
        "runtimeMinutes": "78",
        "genres": "Adventure,Fantasy,Horror"
    },
    {
        "tconst": "tt0145529",
        "titleType": "movie",
        "primaryTitle": "Time Chasers",
        "originalTitle": "Time Chasers",
        "isAdult": "0",
        "startYear": "1994",
        "endYear": "\\N",
        "runtimeMinutes": "89",
        "genres": "Sci-Fi"
    },
    {
        "tconst": "tt0174685",
        "titleType": "movie",
        "primaryTitle": "Girl in Gold Boots",
        "originalTitle": "Girl in Gold Boots",
        "isAdult": "0",
        "startYear": "1968",
        "endYear": "\\N",
        "runtimeMinutes": "94",
        "genres": "Crime,Drama,Music"
    },
    {
        "tconst": "tt0174917",
        "titleType": "video",
        "primaryTitle": "Merlin's Shop of Mystical Wonders",
        "originalTitle": "Merlin's Shop of Mystical Wonders",
        "isAdult": "0",
        "startYear": "1996",
        "endYear": "\\N",
        "runtimeMinutes": "92",
        "genres": "Fantasy,Horror"
    },
    {
        "tconst": "tt0586012",
        "titleType": "tvEpisode",
        "primaryTitle": "Smithereens",
        "originalTitle": "Smithereens",
        "isAdult": "0",
        "startYear": "1976",
        "endYear": "\\N",
        "runtimeMinutes": "60",
        "genres": "Action,Adventure,Sci-Fi"
    },
    {
        "tconst": "tt0643069",
        "titleType": "tvEpisode",
        "primaryTitle": "Hostages",
        "originalTitle": "Hostages",
        "isAdult": "0",
        "startYear": "1984",
        "endYear": "\\N",
        "runtimeMinutes": "\\N",
        "genres": "Action,Adventure,Drama"
    },
    {
        "tconst": "tt0643072",
        "titleType": "tvEpisode",
        "primaryTitle": "Max",
        "originalTitle": "Max",
        "isAdult": "0",
        "startYear": "1984",
        "endYear": "\\N",
        "runtimeMinutes": "60",
        "genres": "Action,Adventure,Drama"
    },
    {
        "tconst": "tt0643073",
        "titleType": "tvEpisode",
        "primaryTitle": "Out-of-Time-Step",
        "originalTitle": "Out-of-Time-Step",
        "isAdult": "0",
        "startYear": "1984",
        "endYear": "\\N",
        "runtimeMinutes": "45",
        "genres": "Action,Adventure,Drama"
    },
    {
        "tconst": "tt0643075",
        "titleType": "tvEpisode",
        "primaryTitle": "State of the Union",
        "originalTitle": "State of the Union",
        "isAdult": "0",
        "startYear": "1984",
        "endYear": "\\N",
        "runtimeMinutes": "\\N",
        "genres": "Action,Adventure,Drama"
    },
    {
        "tconst": "tt1272026",
        "titleType": "tvMovie",
        "primaryTitle": "Revenge of the Mysterons from Mars",
        "originalTitle": "Revenge of the Mysterons from Mars",
        "isAdult": "0",
        "startYear": "1981",
        "endYear": "\\N",
        "runtimeMinutes": "91",
        "genres": "Action,Family,Sci-Fi"
    }
]